ALR32XX/ALR32XX.py
ALR32XX/Library_ALR32XX.py
ALR32XX/__init__.py
Library_ALR32XX-1.2.2.dist-info/LICENCE.txt
Library_ALR32XX-1.2.2.dist-info/METADATA
Library_ALR32XX-1.2.2.dist-info/WHEEL
Library_ALR32XX-1.2.2.dist-info/top_level.txt
Library_ALR32XX-1.2.2.dist-info/RECORD
