Metadata-Version: 2.1
Name: Library-ALR32XX
Version: 1.2.2
Summary: Ce module permet de commander via liaison série les alimentations programmables ALR32XX de ELC
Home-page: https://github.com/elc-construction-electronique/Librairie-Python-ALR32XX
Author: elc-construction-electronique
Author-email: be@elc.fr
License: UNKNOWN
Project-URL: Bug Tracker, https://github.com/elc-construction-electronique/Librairie-Python-ALR32XX
Platform: UNKNOWN
Classifier: Programming Language :: Python :: 3
Classifier: License :: OSI Approved :: MIT License
Classifier: Operating System :: OS Independent
Requires-Python: >=3.6
